{"id": [1, 0], "err": ["", ""], "init-board": "", "user": ["Artificial Idiot V0\n", "Artificial Idiot V0\n"], "step": ["red 0 5\n", "red 8 5\n", "red 0 4\n", "red 8 4\n", "red 0 5\n", "red 8 5\n", "red 0 4\n", "red 8 4\n", "red 0 5\n", "red 8 5\n", "red 0 4\n", "red 8 4\n", "red 0 5\n", "red 8 5\n", "red 0 4\n", "red 8 4\n", "red 0 5\n", "red 8 5\n", "red 0 4\n", "red 8 4\n", "red 0 5\n", "red 8 5\n", "red 0 4\n", "red 8 4\n", "red 0 5\n", "red 8 5\n", "red 0 4\n", "red 8 4\n", "red 0 5\n", "red 8 5\n", "red 0 4\n", "red 8 4\n", "red 0 5\n", "red 8 5\n", "red 0 4\n", "red 8 4\n", "red 0 5\n", "red 8 5\n", "red 0 4\n", "red 8 4\n", "red 0 5\n", "red 8 5\n", "red 0 4\n", "red 8 4\n", "red 0 5\n", "red 8 5\n", "red 0 4\n", "red 8 4\n", "red 0 5\n", "red 8 5\n", "red 0 4\n", "red 8 4\n", "red 0 5\n", "red 8 5\n", "red 0 4\n", "red 8 4\n", "red 0 5\n", "red 8 5\n", "red 0 4\n", "red 8 4\n", "red 0 5\n", "red 8 5\n", "red 0 4\n", "red 8 4\n", "red 0 5\n", "red 8 5\n", "red 0 4\n", "red 8 4\n", "red 0 5\n", "red 8 5\n", "red 0 4\n", "red 8 4\n", "red 0 5\n", "red 8 5\n", "red 0 4\n", "red 8 4\n", "red 0 5\n", "red 8 5\n", "red 0 4\n", "red 8 4\n", "red 0 5\n", "red 8 5\n", "red 0 4\n", "red 8 4\n", "red 0 5\n", "red 8 5\n", "red 0 4\n", "red 8 4\n", "red 0 5\n", "red 8 5\n", "red 0 4\n", "red 8 4\n", "red 0 5\n", "red 8 5\n", "red 0 4\n", "red 8 4\n", "red 0 5\n", "red 8 5\n", "red 0 4\n", "red 8 4\n", "red 0 5\n"], "total": 101, "result": 2}